chameleondump/__init__.py
chameleondump/__main__.py
chameleondump/chameleondump.py
chameleondump/devices/__init__.py
chameleondump/devices/base_device.py
chameleondump/devices/chameleon_ultra.py
chameleondump/utils/__init__.py
chameleondump/utils/ble_utils.py
chameleondump/utils/print_with_color.py
chameleondump-0.1.5.dist-info/LICENSE
chameleondump-0.1.5.dist-info/METADATA
chameleondump-0.1.5.dist-info/WHEEL
chameleondump-0.1.5.dist-info/entry_points.txt
chameleondump-0.1.5.dist-info/top_level.txt
chameleondump-0.1.5.dist-info/RECORD
