Metadata-Version: 2.1
Name: chameleondump
Version: 0.1.5
Summary: Dump RFID tag IDs from ChameleonUltra devices
Home-page: https://github.com/masasron/chameleondump
Author: Ron Masas
License: GNU GPLv3
Keywords: RFID,NFC,ChameleonUltra,ChameleonMini,BLE,Bluetooth
License-File: LICENSE
Requires-Dist: bleak ==0.21.0
Requires-Dist: termcolor ==2.3.0
